ARTcore/ModuleDefects.py
ARTcore/ModuleDetector.py
ARTcore/ModuleGeometry.py
ARTcore/ModuleMask.py
ARTcore/ModuleMirror.py
ARTcore/ModuleOpticalChain.py
ARTcore/ModuleOpticalElement.py
ARTcore/ModuleOpticalRay.py
ARTcore/ModuleProcessing.py
ARTcore/ModuleSource.py
ARTcore/ModuleSupport.py
ARTcore/ModuleZernike.py
ARTcore/__init__.py
AttosecondRayTracing_core-0.92.dist-info/LICENSE
AttosecondRayTracing_core-0.92.dist-info/METADATA
AttosecondRayTracing_core-0.92.dist-info/WHEEL
AttosecondRayTracing_core-0.92.dist-info/top_level.txt
AttosecondRayTracing_core-0.92.dist-info/RECORD
