Metadata-Version: 2.1
Name: AttosecondRayTracing_core
Version: 0.92
Summary: Attosecond Ray Tracing core calculation package
Author: Anthony Guillaume
Author-email: Stefan Haessler <stefan.haessler@ensta-paris.fr>, André Kalouguine <andre.kalouguine@ensta-paris.fr>
Project-URL: Homepage, https://github.com/mightymightys/AttosecondRaytracing
Classifier: Programming Language :: Python :: 3
Classifier: Operating System :: OS Independent
Requires-Python: >=3.8
License-File: LICENSE
Requires-Dist: numpy
Requires-Dist: numpy-quaternion
Requires-Dist: scipy
